headless/__init__.py
headless/apps.py
headless/registry.py
headless/rest/__init__.py
headless/rest/apps.py
headless/rest/authentication.py
headless/rest/builder.py
headless/rest/filters.py
headless/rest/pagination.py
headless/rest/routers.py
headless/rest/serializers.py
headless/rest/urls.py
headless/rest/viewsets.py
headless/settings.py
headless/test_settings.py
headless/tests.py
headless/utils.py
django_headless-1.0.0b6.dist-info/LICENSE
django_headless-1.0.0b6.dist-info/METADATA
django_headless-1.0.0b6.dist-info/WHEEL
django_headless-1.0.0b6.dist-info/RECORD
