Metadata-Version: 2.3
Name: django-headless
Version: 1.0.0b6
Summary: Automagically create a REST API for your Django models
License: MIT
Author: Leon van der Grient
Author-email: leon@devtastic.io
Requires-Python: >=3.10
Classifier: License :: OSI Approved :: MIT License
Classifier: Programming Language :: Python :: 3
Classifier: Programming Language :: Python :: 3.10
Classifier: Programming Language :: Python :: 3.11
Classifier: Programming Language :: Python :: 3.12
Classifier: Programming Language :: Python :: 3.13
Requires-Dist: drf-flex-fields (>=1.0.0,<2.0.0)
Requires-Dist: rich
